tap_shiftbase/__init__.py
tap_shiftbase/client.py
tap_shiftbase/schemas/absentee_options.json
tap_shiftbase/schemas/absentees.json
tap_shiftbase/schemas/contract_types.json
tap_shiftbase/schemas/custom_fields.json
tap_shiftbase/schemas/departments.json
tap_shiftbase/schemas/docs.json
tap_shiftbase/schemas/locations.json
tap_shiftbase/schemas/rosters.json
tap_shiftbase/schemas/shifts.json
tap_shiftbase/schemas/teams.json
tap_shiftbase/schemas/timesheets.json
tap_shiftbase/schemas/users.json
tap_shiftbase/streams.py
tap_shiftbase/tap.py
tap_shiftbase-1.0.1.dist-info/METADATA
tap_shiftbase-1.0.1.dist-info/WHEEL
tap_shiftbase-1.0.1.dist-info/entry_points.txt
tap_shiftbase-1.0.1.dist-info/RECORD
