Metadata-Version: 2.1
Name: tap-shiftbase
Version: 1.0.1
Summary: `tap-shiftbase` is a Singer tap for shiftbase, built with the Meltano Singer SDK.
License: Apache 2.0
Keywords: ELT,shiftbase
Author: Hidde Stokvis
Requires-Python: >=3.7.1,<3.12
Classifier: License :: Other/Proprietary License
Classifier: Programming Language :: Python :: 3
Classifier: Programming Language :: Python :: 3.8
Classifier: Programming Language :: Python :: 3.9
Classifier: Programming Language :: Python :: 3.10
Classifier: Programming Language :: Python :: 3.11
Provides-Extra: s3
Requires-Dist: fs-s3fs (>=1.1.1,<2.0.0) ; extra == "s3"
Requires-Dist: requests (>=2.28.2,<3.0.0)
Requires-Dist: singer-sdk (>=0.23.0,<0.24.0)
